aclib/images/__init__.py
aclib/images/__API__/color.py
aclib/images/__API__/dotset.py
aclib/images/__API__/dotsetlib.py
aclib/images/__API__/dsetsimmat.py
aclib/images/__API__/image.py
aclib/images/__API__/target.py
aclib.images-1.0.0.dist-info/LICENSE
aclib.images-1.0.0.dist-info/METADATA
aclib.images-1.0.0.dist-info/WHEEL
aclib.images-1.0.0.dist-info/top_level.txt
aclib.images-1.0.0.dist-info/RECORD
